scamp_extensions/__init__.py
scamp_extensions/composers/__init__.py
scamp_extensions/composers/barlicity.py
scamp_extensions/engraving/__init__.py
scamp_extensions/engraving/note_graph.py
scamp_extensions/interaction/__init__.py
scamp_extensions/interaction/key_plane.py
scamp_extensions/parsing/__init__.py
scamp_extensions/parsing/midi.py
scamp_extensions/pitch/__init__.py
scamp_extensions/pitch/scale.py
scamp_extensions/pitch/utilities.py
scamp_extensions/playback/__init__.py
scamp_extensions/playback/multi_preset_instrument.py
scamp_extensions/playback/supercollider/__init__.py
scamp_extensions/playback/supercollider/scInit.scd
scamp_extensions/playback/supercollider/sc_lang.py
scamp_extensions/playback/supercollider/sc_playback_implementation.py
scamp_extensions/playback/supercollider/scamp_sc_config.yaml
scamp_extensions/playback/supercollider/scampExtensions/ScampExtensions.sc
scamp_extensions/process/__init__.py
scamp_extensions/process/_pykov.py
scamp_extensions/process/generators.py
scamp_extensions/process/l_systems.py
scamp_extensions/process/markov.py
scamp_extensions/rhythm/__init__.py
scamp_extensions/rhythm/boolean_streamer.py
scamp_extensions/rhythm/indispensability.py
scamp_extensions/rhythm/metric_structure.py
scamp_extensions/utilities/__init__.py
scamp_extensions/utilities/math.py
scamp_extensions/utilities/sequences.py
scamp_extensions/utilities/time_varying_parameter.py
scamp_extensions-0.3.5.post2.dist-info/LICENSE
scamp_extensions-0.3.5.post2.dist-info/METADATA
scamp_extensions-0.3.5.post2.dist-info/WHEEL
scamp_extensions-0.3.5.post2.dist-info/top_level.txt
scamp_extensions-0.3.5.post2.dist-info/RECORD
