Metadata-Version: 2.1
Name: scamp-extensions
Version: 0.3.5.post2
Summary: Extensions to SCAMP (Suite for Computer-Assisted Music in Python)
Home-page: https://git.sr.ht/~marcevanstein/scamp_extensions
Author: Marc Evanstein
Author-email: marc@marcevanstein.com
License: GNU GPL Version 3
Platform: UNKNOWN
Classifier: Programming Language :: Python :: 3.10
Classifier: License :: OSI Approved :: GNU General Public License v3 (GPLv3)
Classifier: Operating System :: OS Independent
Requires-Python: >=3.10
License-File: LICENSE
Requires-Dist: scamp (>=0.9.2)
